livechat/__init__.py
livechat/config.py
livechat/agent/__init__.py
livechat/agent/rtm/__init__.py
livechat/agent/rtm/base.py
livechat/agent/rtm/api/__init__.py
livechat/agent/rtm/api/v33.py
livechat/agent/rtm/api/v34.py
livechat/agent/rtm/api/v35.py
livechat/agent/rtm/api/v36.py
livechat/agent/web/__init__.py
livechat/agent/web/base.py
livechat/agent/web/api/__init__.py
livechat/agent/web/api/v33.py
livechat/agent/web/api/v34.py
livechat/agent/web/api/v35.py
livechat/agent/web/api/v36.py
livechat/billing/__init__.py
livechat/billing/base.py
livechat/billing/api/__init__.py
livechat/billing/api/v1.py
livechat/configuration/__init__.py
livechat/configuration/base.py
livechat/configuration/api/__init__.py
livechat/configuration/api/v33.py
livechat/configuration/api/v34.py
livechat/configuration/api/v35.py
livechat/configuration/api/v36.py
livechat/customer/__init__.py
livechat/customer/rtm/__init__.py
livechat/customer/rtm/base.py
livechat/customer/rtm/api/__init__.py
livechat/customer/rtm/api/v33.py
livechat/customer/rtm/api/v34.py
livechat/customer/rtm/api/v35.py
livechat/customer/rtm/api/v36.py
livechat/customer/web/__init__.py
livechat/customer/web/base.py
livechat/customer/web/api/__init__.py
livechat/customer/web/api/v33.py
livechat/customer/web/api/v34.py
livechat/customer/web/api/v35.py
livechat/customer/web/api/v36.py
livechat/reports/__init__.py
livechat/reports/base.py
livechat/reports/api/__init__.py
livechat/reports/api/v33.py
livechat/reports/api/v34.py
livechat/reports/api/v35.py
livechat/reports/api/v36.py
livechat/utils/__init__.py
livechat/utils/helpers.py
livechat/utils/http_client.py
livechat/utils/httpx_logger.py
livechat/utils/structures.py
livechat/utils/ws_client.py
livechat/webhooks/__init__.py
livechat/webhooks/parser.py
livechat/webhooks/v33.py
livechat/webhooks/v34.py
livechat/webhooks/v35.py
livechat/webhooks/v36.py
lc_sdk_python-0.4.1.dist-info/LICENSE
lc_sdk_python-0.4.1.dist-info/METADATA
lc_sdk_python-0.4.1.dist-info/WHEEL
lc_sdk_python-0.4.1.dist-info/top_level.txt
lc_sdk_python-0.4.1.dist-info/RECORD
