Metadata-Version: 2.1
Name: lc-sdk-python
Version: 0.4.1
Summary: Package which lets to work with LiveChat API.
Home-page: https://github.com/livechat/lc-sdk-python
Author: LiveChat
Author-email: apiteam.qa@livechat.com
License: Apache-2.0
Classifier: License :: OSI Approved :: Apache Software License
Classifier: Operating System :: OS Independent
Classifier: Programming Language :: Python :: 3
Classifier: Programming Language :: Python :: 3 :: Only
Classifier: Programming Language :: Python :: 3.6
Classifier: Programming Language :: Python :: 3.7
Classifier: Programming Language :: Python :: 3.8
Classifier: Programming Language :: Python :: 3.9
Requires-Python: >=3.6
License-File: LICENSE
Requires-Dist: websocket-client ==1.8.0
Requires-Dist: httpx ==0.28.1
Provides-Extra: httpx
Requires-Dist: http2 ; extra == 'httpx'
